cmdict/__init__.py
cmdict/__main__.py
cmdict/ecdict_connector.py
cmdict/history.py
cmdict/pdf_tools.py
cmdict/run_script.py
cmdict/txt_tools.py
cmdict/utils.py
cmdict-0.1.10.dist-info/LICENSE
cmdict-0.1.10.dist-info/METADATA
cmdict-0.1.10.dist-info/WHEEL
cmdict-0.1.10.dist-info/entry_points.txt
cmdict-0.1.10.dist-info/RECORD
