Metadata-Version: 2.1
Name: cmdict
Version: 0.1.10
Summary: A command line dictionary toolset.
Home-page: https://github.com/pastydev/cmdict
License: GPL-3.0
Author: zequnyu
Author-email: zequnyu11@gmail.com
Requires-Python: >=3.8.0,<4.0
Classifier: License :: OSI Approved :: GNU General Public License v3 (GPLv3)
Classifier: Programming Language :: Python :: 3
Classifier: Programming Language :: Python :: 3.8
Classifier: Programming Language :: Python :: 3.9
Classifier: Programming Language :: Python :: 3.10
Classifier: Programming Language :: Python :: 3.11
Requires-Dist: click (>=7.1.2)
Requires-Dist: colorama (>=0.4.3)
Requires-Dist: loguru (>=0.5.1)
Requires-Dist: pyyaml (>=5.3.1)
Requires-Dist: requests (>=2.24.0)
Requires-Dist: tqdm (>=4.48.0)
Requires-Dist: trogon (>=0.5.0,<0.6.0)
Project-URL: Repository, https://github.com/pastydev/cmdict
